alchemyrpcs/__init__.py
alchemyrpcs/alchemyrpcs.py
alchemyrpcs-1.1.8.dist-info/METADATA
alchemyrpcs-1.1.8.dist-info/WHEEL
alchemyrpcs-1.1.8.dist-info/top_level.txt
alchemyrpcs-1.1.8.dist-info/RECORD
