Metadata-Version: 2.1
Name: alchemyrpcs
Version: 1.1.8
Summary: web automation for web3
Home-page: https://github.com/username/my_package
Author: zizian
Classifier: Programming Language :: Python :: 3
Classifier: License :: OSI Approved :: MIT License
Classifier: Operating System :: OS Independent
Requires-Python: >=3.6
